[
    {
        "plasma_discharge": {
            "shot_number": 1160616027,
            "plasma_current": 0.51,
            "line_averaged_density": 2.82,
            "greenwald_fraction": 0.8,
            "t_start": 1.15,
            "t_end": 1.45,
            "duration": 0.3,
            "mlp_mode": "-",
            "confinement_more": "L"
        },
        "blob_parameters": {
            "vx_c": 588.6609541100644,
            "vy_c": 55.71016033383597,
            "area_c": 0.00013207233765462684,
            "vx_tde": 627.0892524277865,
            "vy_tde": -255.2703903328504,
            "lx_f": 0.006131651833927345,
            "ly_f": 0.003199891529490713,
            "theta_f": 0.9080677875680202,
            "taud_psd": 1.886068749748504e-05,
            "lambda_psd": 1.250957390350406e-06,
            "number_events": 1081
        }
    },
    {
        "plasma_discharge": {
            "shot_number": 1160616026,
            "plasma_current": 0.51,
            "line_averaged_density": 2.83,
            "greenwald_fraction": 0.8,
            "t_start": 1.15,
            "t_end": 1.45,
            "duration": 0.3,
            "mlp_mode": "-",
            "confinement_more": "L"
        },
        "blob_parameters": {
            "vx_c": 577.2934619518668,
            "vy_c": 2.0661650504892406,
            "area_c": 0.00013415516520452498,
            "vx_tde": 618.1671010023314,
            "vy_tde": -262.72403833984515,
            "lx_f": 0.007049313197749119,
            "ly_f": 0.0035737341915340437,
            "theta_f": 0.9793453807739183,
            "taud_psd": 1.76988279991519e-05,
            "lambda_psd": 1.0228622852838853e-06,
            "number_events": 1076
        }
    },
    {
        "plasma_discharge": {
            "shot_number": 1160616025,
            "plasma_current": 0.51,
            "line_averaged_density": 2.76,
            "greenwald_fraction": 0.8,
            "t_start": 1.15,
            "t_end": 1.45,
            "duration": 0.3,
            "mlp_mode": "-",
            "confinement_more": "L"
        },
        "blob_parameters": {
            "vx_c": 573.0629100513754,
            "vy_c": 16.878447309276925,
            "area_c": 0.00013589518341214092,
            "vx_tde": 625.6575602299055,
            "vy_tde": -264.99500276681744,
            "lx_f": 0.006551206300945327,
            "ly_f": 0.0036381145350505807,
            "theta_f": 0.8712218677954405,
            "taud_psd": 2.0342679679263842e-05,
            "lambda_psd": 1.1611568656664552e-06,
            "number_events": 1037
        }
    },
    {
        "plasma_discharge": {
            "shot_number": 1160616022,
            "plasma_current": 0.52,
            "line_averaged_density": 2.29,
            "greenwald_fraction": 0.65,
            "t_start": 1.15,
            "t_end": 1.45,
            "duration": 0.3,
            "mlp_mode": "scan",
            "confinement_more": "L"
        },
        "blob_parameters": {
            "vx_c": 500.6663704279154,
            "vy_c": 21.4985298940367,
            "area_c": 0.00013545897620820236,
            "vx_tde": 615.7623547006156,
            "vy_tde": -264.7022868872409,
            "lx_f": 0.005247482230239664,
            "ly_f": 0.0030342242887854633,
            "theta_f": 0.9667926719220532,
            "taud_psd": 3.94410939169032e-05,
            "lambda_psd": 1.048465477305439e-06,
            "number_events": 1216
        }
    },
    {
        "plasma_discharge": {
            "shot_number": 1160616018,
            "plasma_current": 0.53,
            "line_averaged_density": 1.65,
            "greenwald_fraction": 0.46,
            "t_start": 1.15,
            "t_end": 1.45,
            "duration": 0.3,
            "mlp_mode": "dwell",
            "confinement_more": "L"
        },
        "blob_parameters": {
            "vx_c": 483.60525483548344,
            "vy_c": 88.58689425181377,
            "area_c": 0.00010241260783501734,
            "vx_tde": 598.0203132393294,
            "vy_tde": -238.5990064492176,
            "lx_f": 0.0043175821123817345,
            "ly_f": 0.002936369344519174,
            "theta_f": 0.737303600918597,
            "taud_psd": 2.4955675859084092e-05,
            "lambda_psd": 1.106438075878942e-06,
            "number_events": 1385
        }
    },
    {
        "plasma_discharge": {
            "shot_number": 1160616017,
            "plasma_current": 0.53,
            "line_averaged_density": 1.56,
            "greenwald_fraction": 0.44,
            "t_start": 1.15,
            "t_end": 1.45,
            "duration": 0.3,
            "mlp_mode": "scan",
            "confinement_more": "L"
        },
        "blob_parameters": {
            "vx_c": 466.1561006483469,
            "vy_c": 76.777947342567,
            "area_c": 0.0001043353120936855,
            "vx_tde": 585.1623604313426,
            "vy_tde": -235.9368298898979,
            "lx_f": 0.004512214246122763,
            "ly_f": 0.002808459334072828,
            "theta_f": 0.8362815045332619,
            "taud_psd": 2.585920531791852e-05,
            "lambda_psd": 1.491352851376568e-06,
            "number_events": 1384
        }
    },
    {
        "plasma_discharge": {
            "shot_number": 1160616016,
            "plasma_current": 0.53,
            "line_averaged_density": 1.6,
            "greenwald_fraction": 0.45,
            "t_start": 1.15,
            "t_end": 1.45,
            "duration": 0.3,
            "mlp_mode": "scan",
            "confinement_more": "L"
        },
        "blob_parameters": {
            "vx_c": 477.13978298014365,
            "vy_c": 90.52264025335609,
            "area_c": 9.986638495570858e-05,
            "vx_tde": 592.2925194731631,
            "vy_tde": -237.37143822487033,
            "lx_f": 0.0031365836086386036,
            "ly_f": 0.0033648917282057887,
            "theta_f": 0.12131049132794247,
            "taud_psd": 2.5282475199367438e-05,
            "lambda_psd": 1.1881542155438063e-06,
            "number_events": 1353
        }
    },
    {
        "plasma_discharge": {
            "shot_number": 1160616011,
            "plasma_current": 0.54,
            "line_averaged_density": 1.07,
            "greenwald_fraction": 0.3,
            "t_start": 1.15,
            "t_end": 1.45,
            "duration": 0.3,
            "mlp_mode": "scan",
            "confinement_more": "L"
        },
        "blob_parameters": {
            "vx_c": 412.64311503655534,
            "vy_c": 37.74803586669205,
            "area_c": 9.587951720765304e-05,
            "vx_tde": 502.0228553534614,
            "vy_tde": -237.15218162924094,
            "lx_f": 0.0044350075911559015,
            "ly_f": 0.0024031969683891317,
            "theta_f": 0.794467747002396,
            "taud_psd": 1.6962246868951203e-05,
            "lambda_psd": 0.1516184839100769,
            "number_events": 1373
        }
    },
    {
        "plasma_discharge": {
            "shot_number": 1160616009,
            "plasma_current": 0.54,
            "line_averaged_density": 0.87,
            "greenwald_fraction": 0.24,
            "t_start": 1.305,
            "t_end": 1.45,
            "duration": 0.145,
            "mlp_mode": "scan",
            "confinement_more": "L"
        },
        "blob_parameters": {
            "vx_c": 463.4902134752169,
            "vy_c": 141.9703131984279,
            "area_c": 8.846074508539444e-05,
            "vx_tde": 457.5705047967853,
            "vy_tde": -165.9718673967418,
            "lx_f": 0.003914766467171006,
            "ly_f": 0.00279647340229782,
            "theta_f": 0.7922549986246172,
            "taud_psd": 1.7608417828746115e-05,
            "lambda_psd": 0.161364653404793,
            "number_events": 659
        }
    }
]